{"caseSensitive":true,"concept":[{"code":"single","definition":"The item may only be selected one time","display":"Single"},{"code":"multiple","definition":"The item may be selected multiple times","display":"Multiple"}],"contact":[{"telecom":[{"system":"other","value":"http://hl7.org/fhir"},{"system":"email","value":"fhir@lists.hl7.org"}]}],"content":"complete","date":"2016-03-31T08:01:25+11:00","description":"Defines behavior for an action or a group for how many times that item may be repeated","experimental":false,"extension":[{"url":"http://hl7.org/fhir/StructureDefinition/valueset-oid","valueUri":"urn:oid:2.16.840.1.113883.4.642.1.507"}],"id":"cardinality-behavior","meta":{"lastUpdated":"2016-03-31T08:01:25.570+11:00"},"name":"OrderSetItemCardinalityBehavior","publisher":"HL7 (FHIR Project)","resourceType":"CodeSystem","status":"draft","text":{"div":"<div><h2>OrderSetItemCardinalityBehavior</h2><p>Defines behavior for an action or a group for how many times that item may be repeated</p><p>This code system http://hl7.org/fhir/cardinality-behavior defines the following codes:</p><table class=\"codes\"><tr><td><b>Code</b></td><td><b>Display</b></td><td><b>Definition</b></td></tr><tr><td>single<a name=\"single\"> </a></td><td>Single</td><td>The item may only be selected one time</td></tr><tr><td>multiple<a name=\"multiple\"> </a></td><td>Multiple</td><td>The item may be selected multiple times</td></tr></table></div>","status":"generated"},"url":"http://hl7.org/fhir/cardinality-behavior","valueSet":"http://hl7.org/fhir/ValueSet/cardinality-behavior","version":"1.4.0"}